fleetmaster/__init__.py
fleetmaster/cli.py
fleetmaster/logging_setup.py
fleetmaster/commands/__init__.py
fleetmaster/commands/gui.py
fleetmaster/commands/list.py
fleetmaster/commands/run.py
fleetmaster/commands/view.py
fleetmaster/core/__init__.py
fleetmaster/core/engine.py
fleetmaster/core/exceptions.py
fleetmaster/core/io.py
fleetmaster/core/settings.py
fleetmaster/gui/__init__.py
fleetmaster/gui/handles.py
fleetmaster/gui/main_window.py
fleetmaster-0.2.1.dist-info/licenses/LICENSE
fleetmaster-0.2.1.dist-info/METADATA
fleetmaster-0.2.1.dist-info/WHEEL
fleetmaster-0.2.1.dist-info/entry_points.txt
fleetmaster-0.2.1.dist-info/top_level.txt
fleetmaster-0.2.1.dist-info/RECORD
